{
  "pushed_at": "2026-05-27T10:34:51Z",
  "events": [
    {
      "timestamp": "2026-05-27T10:30:28Z",
      "bot": "server",
      "category": "user_update",
      "action": "user_profile_changed",
      "actor": null,
      "target": {
        "id": "939071070818926632",
        "name": "ritql",
        "discriminator": "0",
        "display_name": "ritql",
        "bot": false,
        "system": false,
        "avatar_url": "https://cdn.discordapp.com/avatars/939071070818926632/5914fa00c3eff4da73e4435363889ac5.png?size=1024",
        "public_flags": 64,
        "public_flag_names": [
          "hypesquad_bravery"
        ],
        "created_at": "2022-02-04T08:13:10.380000+00:00"
      },
      "details": {
        "changes": {
          "avatar_url": {
            "before": "https://cdn.discordapp.com/avatars/939071070818926632/41ead0b1e8eed7d231c8f7db8d0704b3.png?size=1024",
            "after": "https://cdn.discordapp.com/avatars/939071070818926632/5914fa00c3eff4da73e4435363889ac5.png?size=1024"
          }
        }
      },
      "guild_id": null,
      "guild_name": null
    },
    {
      "timestamp": "2026-05-27T10:31:04Z",
      "bot": "server",
      "category": "user_update",
      "action": "user_profile_changed",
      "actor": null,
      "target": {
        "id": "1195703017782120554",
        "name": "247loosey",
        "discriminator": "0",
        "global_name": "GrpDjes",
        "display_name": "GrpDjes",
        "bot": false,
        "system": false,
        "avatar_url": "https://cdn.discordapp.com/avatars/1195703017782120554/46322794eee63ff1fcbc56495a6d49c1.png?size=1024",
        "public_flags": 0,
        "public_flag_names": [],
        "created_at": "2024-01-13T12:16:54.527000+00:00"
      },
      "details": {
        "changes": {
          "global_name": {
            "before": "Djes",
            "after": "GrpDjes"
          }
        }
      },
      "guild_id": null,
      "guild_name": null
    },
    {
      "timestamp": "2026-05-27T10:32:13Z",
      "bot": "server",
      "category": "user_update",
      "action": "user_profile_changed",
      "actor": null,
      "target": {
        "id": "982397704162398218",
        "name": "ssonicumar3426",
        "discriminator": "0",
        "global_name": "pablo",
        "display_name": "pablo",
        "bot": false,
        "system": false,
        "avatar_url": "https://cdn.discordapp.com/avatars/982397704162398218/ef44f4ea1a28c3869967cbdf6a379b5c.png?size=1024",
        "public_flags": 0,
        "public_flag_names": [],
        "created_at": "2022-06-03T21:37:44.739000+00:00"
      },
      "details": {
        "changes": {
          "avatar_url": {
            "before": "https://cdn.discordapp.com/avatars/982397704162398218/c1f5c7d0e3e3f0143fe6cf3e4d09a1b6.png?size=1024",
            "after": "https://cdn.discordapp.com/avatars/982397704162398218/ef44f4ea1a28c3869967cbdf6a379b5c.png?size=1024"
          }
        }
      },
      "guild_id": null,
      "guild_name": null
    },
    {
      "timestamp": "2026-05-27T10:32:45Z",
      "bot": "server",
      "category": "user_update",
      "action": "user_profile_changed",
      "actor": null,
      "target": {
        "id": "1068176905741795348",
        "name": "vl.by",
        "discriminator": "0",
        "global_name": "\u1cbc",
        "display_name": "\u1cbc",
        "bot": false,
        "system": false,
        "avatar_url": "https://cdn.discordapp.com/avatars/1068176905741795348/af98191b7be430a7bd79bdd2aced192f.png?size=1024",
        "public_flags": 256,
        "public_flag_names": [
          "hypesquad_balance"
        ],
        "created_at": "2023-01-26T14:33:40.096000+00:00"
      },
      "details": {
        "changes": {
          "avatar_url": {
            "before": "https://cdn.discordapp.com/avatars/1068176905741795348/c9fd2998fa9c22c2103de5cdf268a6ef.png?size=1024",
            "after": "https://cdn.discordapp.com/avatars/1068176905741795348/af98191b7be430a7bd79bdd2aced192f.png?size=1024"
          }
        }
      },
      "guild_id": null,
      "guild_name": null
    },
    {
      "timestamp": "2026-05-27T10:33:43Z",
      "bot": "server",
      "category": "user_update",
      "action": "user_profile_changed",
      "actor": null,
      "target": {
        "id": "1245097127298727946",
        "name": "richslayher",
        "discriminator": "0",
        "global_name": "richestbritt (noxy)",
        "display_name": "richestbritt (noxy)",
        "bot": false,
        "system": false,
        "avatar_url": "https://cdn.discordapp.com/avatars/1245097127298727946/27854c174102bfd49de90e9127ca786f.png?size=1024",
        "public_flags": 0,
        "public_flag_names": [],
        "created_at": "2024-05-28T19:31:27.934000+00:00"
      },
      "details": {
        "changes": {
          "name": {
            "before": ".richerthanu",
            "after": "richslayher"
          }
        }
      },
      "guild_id": null,
      "guild_name": null
    }
  ]
}