{
  "pushed_at": "2026-05-30T09:44:51Z",
  "events": [
    {
      "timestamp": "2026-05-30T09:40:15Z",
      "bot": "server",
      "category": "user_update",
      "action": "user_profile_changed",
      "actor": null,
      "target": {
        "id": "736020216919621752",
        "name": "7e2ix",
        "discriminator": "0",
        "global_name": "x\u00b2",
        "display_name": "x\u00b2",
        "bot": false,
        "system": false,
        "avatar_url": "https://cdn.discordapp.com/avatars/736020216919621752/579ef1d6e95263351eb750d196796c1c.png?size=1024",
        "public_flags": 128,
        "public_flag_names": [
          "hypesquad_brilliance"
        ],
        "created_at": "2020-07-24T00:41:34.308000+00:00"
      },
      "details": {
        "changes": {
          "global_name": {
            "before": "x\u00b2 - Mikey Bin Khalid",
            "after": "x\u00b2"
          }
        }
      },
      "guild_id": null,
      "guild_name": null
    },
    {
      "timestamp": "2026-05-30T09:41:02Z",
      "bot": "server",
      "category": "user_update",
      "action": "user_profile_changed",
      "actor": null,
      "target": {
        "id": "1268132000171294794",
        "name": "2013panda",
        "discriminator": "0",
        "global_name": "Panda",
        "display_name": "Panda",
        "bot": false,
        "system": false,
        "avatar_url": "https://cdn.discordapp.com/embed/avatars/4.png",
        "public_flags": 0,
        "public_flag_names": [],
        "created_at": "2024-07-31T09:03:49.594000+00:00"
      },
      "details": {
        "changes": {
          "avatar_url": {
            "before": "https://cdn.discordapp.com/avatars/1268132000171294794/e0eabf73c958fca45b7fe3946723e689.png?size=1024",
            "after": "https://cdn.discordapp.com/embed/avatars/4.png"
          }
        }
      },
      "guild_id": null,
      "guild_name": null
    },
    {
      "timestamp": "2026-05-30T09:41:20Z",
      "bot": "server",
      "category": "user_update",
      "action": "user_profile_changed",
      "actor": null,
      "target": {
        "id": "1207663053236076588",
        "name": "jumss.exe",
        "discriminator": "0",
        "global_name": "nhl95",
        "display_name": "nhl95",
        "bot": false,
        "system": false,
        "avatar_url": "https://cdn.discordapp.com/avatars/1207663053236076588/3e24333b5ef882ed792c799a5023492f.png?size=1024",
        "public_flags": 0,
        "public_flag_names": [],
        "created_at": "2024-02-15T12:21:49.186000+00:00"
      },
      "details": {
        "changes": {
          "avatar_url": {
            "before": "https://cdn.discordapp.com/avatars/1207663053236076588/6c566d054ddab500ef8473f43f132331.png?size=1024",
            "after": "https://cdn.discordapp.com/avatars/1207663053236076588/3e24333b5ef882ed792c799a5023492f.png?size=1024"
          }
        }
      },
      "guild_id": null,
      "guild_name": null
    },
    {
      "timestamp": "2026-05-30T09:42:19Z",
      "bot": "server",
      "category": "user_update",
      "action": "user_profile_changed",
      "actor": null,
      "target": {
        "id": "1268132000171294794",
        "name": "2013panda",
        "discriminator": "0",
        "global_name": "Panda",
        "display_name": "Panda",
        "bot": false,
        "system": false,
        "avatar_url": "https://cdn.discordapp.com/avatars/1268132000171294794/8f0d78eda9bde484b0f45869c9ed88fb.png?size=1024",
        "public_flags": 0,
        "public_flag_names": [],
        "created_at": "2024-07-31T09:03:49.594000+00:00"
      },
      "details": {
        "changes": {
          "avatar_url": {
            "before": "https://cdn.discordapp.com/embed/avatars/4.png",
            "after": "https://cdn.discordapp.com/avatars/1268132000171294794/8f0d78eda9bde484b0f45869c9ed88fb.png?size=1024"
          }
        }
      },
      "guild_id": null,
      "guild_name": null
    },
    {
      "timestamp": "2026-05-30T09:42:25Z",
      "bot": "server",
      "category": "user_update",
      "action": "user_profile_changed",
      "actor": null,
      "target": {
        "id": "1438168525255737501",
        "name": "koovi_.",
        "discriminator": "0",
        "global_name": "Koovi",
        "display_name": "Koovi",
        "bot": false,
        "system": false,
        "avatar_url": "https://cdn.discordapp.com/avatars/1438168525255737501/2b7908ac1e9979f893aa16182650e90c.png?size=1024",
        "public_flags": 0,
        "public_flag_names": [],
        "created_at": "2025-11-12T14:08:16.300000+00:00"
      },
      "details": {
        "changes": {
          "avatar_url": {
            "before": "https://cdn.discordapp.com/avatars/1438168525255737501/3d9c4a4e0d7ebc063b5664090524e9f1.png?size=1024",
            "after": "https://cdn.discordapp.com/avatars/1438168525255737501/2b7908ac1e9979f893aa16182650e90c.png?size=1024"
          }
        }
      },
      "guild_id": null,
      "guild_name": null
    },
    {
      "timestamp": "2026-05-30T09:43:10Z",
      "bot": "server",
      "category": "user_update",
      "action": "user_profile_changed",
      "actor": null,
      "target": {
        "id": "1396644442311757876",
        "name": "dgtfps1",
        "discriminator": "0",
        "global_name": "dgt",
        "display_name": "dgt",
        "bot": false,
        "system": false,
        "avatar_url": "https://cdn.discordapp.com/avatars/1396644442311757876/abe79297db4291f5b0c3594b6c1ddf4c.png?size=1024",
        "public_flags": 0,
        "public_flag_names": [],
        "created_at": "2025-07-21T00:06:23.446000+00:00"
      },
      "details": {
        "changes": {
          "global_name": {
            "before": "dgt yechou",
            "after": "dgt"
          }
        }
      },
      "guild_id": null,
      "guild_name": null
    },
    {
      "timestamp": "2026-05-30T09:44:07Z",
      "bot": "server",
      "category": "user_update",
      "action": "user_profile_changed",
      "actor": null,
      "target": {
        "id": "1396644442311757876",
        "name": "dgtfps1",
        "discriminator": "0",
        "global_name": "1dgtshawnn",
        "display_name": "1dgtshawnn",
        "bot": false,
        "system": false,
        "avatar_url": "https://cdn.discordapp.com/avatars/1396644442311757876/abe79297db4291f5b0c3594b6c1ddf4c.png?size=1024",
        "public_flags": 0,
        "public_flag_names": [],
        "created_at": "2025-07-21T00:06:23.446000+00:00"
      },
      "details": {
        "changes": {
          "global_name": {
            "before": "dgt",
            "after": "1dgtshawnn"
          }
        }
      },
      "guild_id": null,
      "guild_name": null
    },
    {
      "timestamp": "2026-05-30T09:44:22Z",
      "bot": "server",
      "category": "user_update",
      "action": "user_profile_changed",
      "actor": null,
      "target": {
        "id": "1396644442311757876",
        "name": "dgtfps1",
        "discriminator": "0",
        "global_name": "dgtshawn",
        "display_name": "dgtshawn",
        "bot": false,
        "system": false,
        "avatar_url": "https://cdn.discordapp.com/avatars/1396644442311757876/abe79297db4291f5b0c3594b6c1ddf4c.png?size=1024",
        "public_flags": 0,
        "public_flag_names": [],
        "created_at": "2025-07-21T00:06:23.446000+00:00"
      },
      "details": {
        "changes": {
          "global_name": {
            "before": "1dgtshawnn",
            "after": "dgtshawn"
          }
        }
      },
      "guild_id": null,
      "guild_name": null
    },
    {
      "timestamp": "2026-05-30T09:44:34Z",
      "bot": "server",
      "category": "user_update",
      "action": "user_profile_changed",
      "actor": null,
      "target": {
        "id": "1396644442311757876",
        "name": "dgtfps1",
        "discriminator": "0",
        "global_name": "dgtshawnn",
        "display_name": "dgtshawnn",
        "bot": false,
        "system": false,
        "avatar_url": "https://cdn.discordapp.com/avatars/1396644442311757876/abe79297db4291f5b0c3594b6c1ddf4c.png?size=1024",
        "public_flags": 0,
        "public_flag_names": [],
        "created_at": "2025-07-21T00:06:23.446000+00:00"
      },
      "details": {
        "changes": {
          "global_name": {
            "before": "dgtshawn",
            "after": "dgtshawnn"
          }
        }
      },
      "guild_id": null,
      "guild_name": null
    }
  ]
}