{
  "pushed_at": "2026-05-28T11:14:51Z",
  "events": [
    {
      "timestamp": "2026-05-28T11:14:12Z",
      "bot": "server",
      "category": "message_delete",
      "action": "raw_message_deleted",
      "actor": null,
      "target": null,
      "details": {
        "message_id": "1507309828471783546",
        "channel_id": "1249416251759919246",
        "note": "message was not in cache \u2014 only IDs available",
        "audit": null
      },
      "guild_id": "1041450125391835186",
      "guild_name": "WAVE Drop Map Staff Hub"
    }
  ]
}