{
  "pushed_at": "2026-05-29T16:04:51Z",
  "events": [
    {
      "timestamp": "2026-05-29T16:00:07Z",
      "bot": "server",
      "category": "reaction_add",
      "action": "reaction_added",
      "actor": {
        "id": "1458092102322880672",
        "name": "slaxmgmt",
        "discriminator": "0",
        "global_name": "Slax",
        "display_name": "Slax",
        "bot": false,
        "system": false,
        "pending": false,
        "avatar_url": "https://cdn.discordapp.com/avatars/1458092102322880672/fef7ab4bc011028b3f08003d2a6e3000.png?size=1024",
        "public_flags": 0,
        "public_flag_names": [],
        "created_at": "2026-01-06T13:37:27.235000+00:00",
        "joined_at": "2026-01-27T03:54:58.490000+00:00",
        "roles": [
          {
            "id": "1496845455588593665",
            "name": "Vote Role",
            "position": 1,
            "color": "#000000"
          },
          {
            "id": "1491225386804314132",
            "name": "*",
            "position": 4,
            "color": "#000000"
          },
          {
            "id": "1470639632583626854",
            "name": "Vbucks",
            "position": 5,
            "color": "#000000"
          },
          {
            "id": "1455057447172444212",
            "name": "Middle East",
            "position": 18,
            "color": "#000000"
          },
          {
            "id": "1443750844636856412",
            "name": "Poll Ping",
            "position": 20,
            "color": "#000000"
          },
          {
            "id": "1201789358336901161",
            "name": "Role Giver",
            "position": 23,
            "color": "#000000"
          },
          {
            "id": "1043664233361051668",
            "name": "7/7 active",
            "position": 29,
            "color": "#000000"
          },
          {
            "id": "1503649126192119839",
            "name": "Loot Route Inspector",
            "position": 30,
            "color": "#000000"
          },
          {
            "id": "1061636163644952576",
            "name": "Drop Map Tester",
            "position": 32,
            "color": "#ffbebf"
          },
          {
            "id": "1417086287025934346",
            "name": "Drop Map Reviewer",
            "position": 33,
            "color": "#1aabbc"
          },
          {
            "id": "1231188006757728266",
            "name": "Loot Route Maker",
            "position": 35,
            "color": "#01665b"
          },
          {
            "id": "1414070590851121254",
            "name": "Surge Route Maker",
            "position": 36,
            "color": "#e7316e"
          },
          {
            "id": "1261142546814468136",
            "name": "Tips and Tricks Helper",
            "position": 37,
            "color": "#af4700"
          },
          {
            "id": "1041582141340917870",
            "name": "Staff",
            "position": 39,
            "color": "#c9ff8b"
          },
          {
            "id": "1041582129500397658",
            "name": "Support",
            "position": 40,
            "color": "#82ffff"
          },
          {
            "id": "1417348281402396703",
            "name": "Senior Support",
            "position": 41,
            "color": "#828fff"
          },
          {
            "id": "1041582116963614781",
            "name": "Admin",
            "position": 43,
            "color": "#a6b4ff"
          },
          {
            "id": "1502630029555925024",
            "name": "Senior Admin",
            "position": 44,
            "color": "#cd9cff"
          },
          {
            "id": "1308389636111859733",
            "name": "Head Admin",
            "position": 45,
            "color": "#f484ff"
          },
          {
            "id": "1466666807183147049",
            "name": "Active Code User",
            "position": 47,
            "color": "#d900ff"
          }
        ],
        "top_role": "Active Code User",
        "guild_permissions": 682390913015360
      },
      "target": null,
      "details": {
        "emoji": "\ud83d\udc4d",
        "emoji_id": null,
        "emoji_name": "\ud83d\udc4d",
        "emoji_animated": false,
        "message_id": "1509949455355351155",
        "channel_id": "1495740476706394194",
        "user_id": "1458092102322880672",
        "burst": false,
        "type": "ReactionType.normal"
      },
      "guild_id": "1041450125391835186",
      "guild_name": "WAVE Drop Map Staff Hub"
    },
    {
      "timestamp": "2026-05-29T16:00:09Z",
      "bot": "server",
      "category": "reaction_add",
      "action": "reaction_added",
      "actor": {
        "id": "1407405613239238719",
        "name": "tayurboy111_222",
        "discriminator": "0",
        "global_name": "Tay ur boy",
        "display_name": "Tay ur boy",
        "bot": false,
        "system": false,
        "pending": false,
        "avatar_url": "https://cdn.discordapp.com/avatars/1407405613239238719/4bc185e9f79251a809166dddacccc1b0.png?size=1024",
        "public_flags": 0,
        "public_flag_names": [],
        "created_at": "2025-08-19T16:47:26.528000+00:00",
        "joined_at": "2026-03-13T13:43:45.611000+00:00",
        "roles": [
          {
            "id": "1496845455588593665",
            "name": "Vote Role",
            "position": 1,
            "color": "#000000"
          },
          {
            "id": "1491225386804314132",
            "name": "*",
            "position": 4,
            "color": "#000000"
          },
          {
            "id": "1470639632583626854",
            "name": "Vbucks",
            "position": 5,
            "color": "#000000"
          },
          {
            "id": "1455057447172444212",
            "name": "Middle East",
            "position": 18,
            "color": "#000000"
          },
          {
            "id": "1443750844636856412",
            "name": "Poll Ping",
            "position": 20,
            "color": "#000000"
          },
          {
            "id": "1214099828389183538",
            "name": "Map Request Helper",
            "position": 22,
            "color": "#000000"
          },
          {
            "id": "1201789358336901161",
            "name": "Role Giver",
            "position": 23,
            "color": "#000000"
          },
          {
            "id": "1043664233361051668",
            "name": "7/7 active",
            "position": 29,
            "color": "#000000"
          },
          {
            "id": "1231188006757728266",
            "name": "Loot Route Maker",
            "position": 35,
            "color": "#01665b"
          },
          {
            "id": "1261142546814468136",
            "name": "Tips and Tricks Helper",
            "position": 37,
            "color": "#af4700"
          },
          {
            "id": "1041582141340917870",
            "name": "Staff",
            "position": 39,
            "color": "#c9ff8b"
          },
          {
            "id": "1041582129500397658",
            "name": "Support",
            "position": 40,
            "color": "#82ffff"
          },
          {
            "id": "1417348281402396703",
            "name": "Senior Support",
            "position": 41,
            "color": "#828fff"
          },
          {
            "id": "1041582116963614781",
            "name": "Admin",
            "position": 43,
            "color": "#a6b4ff"
          },
          {
            "id": "1502630029555925024",
            "name": "Senior Admin",
            "position": 44,
            "color": "#cd9cff"
          },
          {
            "id": "1466666807183147049",
            "name": "Active Code User",
            "position": 47,
            "color": "#d900ff"
          },
          {
            "id": "1211965456643002379",
            "name": "Head Logistics",
            "position": 58,
            "color": "#2c00ff"
          }
        ],
        "top_role": "Head Logistics",
        "guild_permissions": 682390912884288
      },
      "target": null,
      "details": {
        "emoji": "\ud83d\udc4d",
        "emoji_id": null,
        "emoji_name": "\ud83d\udc4d",
        "emoji_animated": false,
        "message_id": "1509949455355351155",
        "channel_id": "1495740476706394194",
        "user_id": "1407405613239238719",
        "burst": false,
        "type": "ReactionType.normal"
      },
      "guild_id": "1041450125391835186",
      "guild_name": "WAVE Drop Map Staff Hub"
    },
    {
      "timestamp": "2026-05-29T16:02:43Z",
      "bot": "server",
      "category": "reaction_add",
      "action": "reaction_added",
      "actor": {
        "id": "821412756729233439",
        "name": "itsdolphin",
        "discriminator": "0",
        "global_name": "It\u2019s Dolphin",
        "display_name": "It\u2019s Dolphin",
        "bot": false,
        "system": false,
        "pending": false,
        "avatar_url": "https://cdn.discordapp.com/avatars/821412756729233439/4225f256d5335a918c48fb825c7e8bdb.png?size=1024",
        "public_flags": 128,
        "public_flag_names": [
          "hypesquad_brilliance"
        ],
        "created_at": "2021-03-16T16:01:02.315000+00:00",
        "joined_at": "2025-12-16T00:32:31.189000+00:00",
        "roles": [
          {
            "id": "1490579498884665425",
            "name": "*",
            "position": 1,
            "color": "#000000"
          },
          {
            "id": "1499037003004772402",
            "name": "Training",
            "position": 2,
            "color": "#000000"
          },
          {
            "id": "1306357759163498496",
            "name": "English \ud83c\uddec\ud83c\udde7",
            "position": 9,
            "color": "#000000"
          },
          {
            "id": "1220671809234407504",
            "name": "Loot Route Maker",
            "position": 15,
            "color": "#000000"
          },
          {
            "id": "1261143275155226746",
            "name": "Tips and Tricks Helper",
            "position": 17,
            "color": "#000000"
          },
          {
            "id": "1408648789363003462",
            "name": "Map Request Helper",
            "position": 18,
            "color": "#000000"
          },
          {
            "id": "1210764292719247400",
            "name": "Twitter",
            "position": 21,
            "color": "#000000"
          },
          {
            "id": "1210764975090438155",
            "name": "Member",
            "position": 22,
            "color": "#ff0000"
          },
          {
            "id": "1305277560086593546",
            "name": "Manual Named Locations",
            "position": 23,
            "color": "#ff8000"
          },
          {
            "id": "1055713830988157039",
            "name": "Manual Landmarks",
            "position": 24,
            "color": "#ffff00"
          },
          {
            "id": "1210770102983856138",
            "name": "Named Locations",
            "position": 25,
            "color": "#ff8000"
          },
          {
            "id": "1210810135249817610",
            "name": "Role Giver",
            "position": 27,
            "color": "#000000"
          },
          {
            "id": "1210819996372959243",
            "name": "Bronze (LVL 5)",
            "position": 29,
            "color": "#bfff00"
          },
          {
            "id": "1210868595635134514",
            "name": "Silver (LVL 10)",
            "position": 30,
            "color": "#40ff00"
          },
          {
            "id": "1210820151629586494",
            "name": "Gold (LVL 15)",
            "position": 31,
            "color": "#00ff40"
          },
          {
            "id": "1210820151646228490",
            "name": "Platinum (LVL 20)",
            "position": 32,
            "color": "#00ffbf"
          },
          {
            "id": "1210851932877357066",
            "name": "Battle Pass Supporter",
            "position": 37,
            "color": "#8000ff"
          },
          {
            "id": "1417086738563858483",
            "name": "Drop Map Reviewer",
            "position": 43,
            "color": "#1aabbc"
          },
          {
            "id": "1407570820695588864",
            "name": "Drop Map Tester",
            "position": 44,
            "color": "#ffbebf"
          },
          {
            "id": "1210803062080409600",
            "name": "Staff",
            "position": 46,
            "color": "#c9ff8b"
          },
          {
            "id": "1210847437728649266",
            "name": "Support",
            "position": 50,
            "color": "#82ffff"
          }
        ],
        "top_role": "Support",
        "guild_permissions": 858446386761537
      },
      "target": null,
      "details": {
        "emoji": "\ud83d\udc4d",
        "emoji_id": null,
        "emoji_name": "\ud83d\udc4d",
        "emoji_animated": false,
        "message_id": "1509934672459599952",
        "channel_id": "1210798761329295440",
        "user_id": "821412756729233439",
        "burst": false,
        "type": "ReactionType.normal"
      },
      "guild_id": "988564962802810961",
      "guild_name": "Wave Free Dropmaps!"
    }
  ]
}