{
  "pushed_at": "2026-05-27T12:29:51Z",
  "events": [
    {
      "timestamp": "2026-05-27T12:26:23Z",
      "bot": "server",
      "category": "reaction_remove",
      "action": "reaction_removed",
      "actor": {
        "id": "1391096191907004459",
        "name": "zunix_43",
        "discriminator": "0",
        "global_name": "z\u1d64\u2099\u1d62\u2093",
        "display_name": "z\u1d64\u2099\u1d62\u2093",
        "bot": false,
        "system": false,
        "avatar_url": "https://cdn.discordapp.com/avatars/1391096191907004459/d61c598210f2b860e512ffa5bc993e51.png?size=1024",
        "public_flags": 0,
        "public_flag_names": [],
        "created_at": "2025-07-05T16:39:37.468000+00:00"
      },
      "target": null,
      "details": {
        "emoji": "\u2764\ufe0f",
        "emoji_id": null,
        "emoji_name": "\u2764\ufe0f",
        "message_id": "1509131532252610612",
        "channel_id": "1210814682357698621",
        "user_id": "1391096191907004459"
      },
      "guild_id": "988564962802810961",
      "guild_name": "Wave Free Dropmaps!"
    }
  ]
}