{
  "pushed_at": "2026-05-29T05:44:51Z",
  "events": [
    {
      "timestamp": "2026-05-29T05:40:05Z",
      "bot": "server",
      "category": "user_update",
      "action": "user_profile_changed",
      "actor": null,
      "target": {
        "id": "1492697048405774436",
        "name": "xzxzxxxzxzxzxxz",
        "discriminator": "0",
        "global_name": ".",
        "display_name": ".",
        "bot": false,
        "system": false,
        "avatar_url": "https://cdn.discordapp.com/avatars/1492697048405774436/9536d11d1680db97c9bba60d157efab2.png?size=1024",
        "public_flags": 0,
        "public_flag_names": [],
        "created_at": "2026-04-12T01:25:09.310000+00:00"
      },
      "details": {
        "changes": {
          "avatar_url": {
            "before": "https://cdn.discordapp.com/avatars/1492697048405774436/7f09329dc740145ddee0f450e9a19387.png?size=1024",
            "after": "https://cdn.discordapp.com/avatars/1492697048405774436/9536d11d1680db97c9bba60d157efab2.png?size=1024"
          }
        }
      },
      "guild_id": null,
      "guild_name": null
    },
    {
      "timestamp": "2026-05-29T05:41:01Z",
      "bot": "server",
      "category": "user_update",
      "action": "user_profile_changed",
      "actor": null,
      "target": {
        "id": "1175800129400357018",
        "name": "loljsisns",
        "discriminator": "0",
        "global_name": "Val0M",
        "display_name": "Val0M",
        "bot": false,
        "system": false,
        "avatar_url": "https://cdn.discordapp.com/avatars/1175800129400357018/ca7e1ca5efc45d0e71ee21128fab402a.png?size=1024",
        "public_flags": 0,
        "public_flag_names": [],
        "created_at": "2023-11-19T14:09:56.159000+00:00"
      },
      "details": {
        "changes": {
          "avatar_url": {
            "before": "https://cdn.discordapp.com/avatars/1175800129400357018/a_7d011a2f6f88491df84ca1245b90c3dc.gif?size=1024",
            "after": "https://cdn.discordapp.com/avatars/1175800129400357018/ca7e1ca5efc45d0e71ee21128fab402a.png?size=1024"
          }
        }
      },
      "guild_id": null,
      "guild_name": null
    },
    {
      "timestamp": "2026-05-29T05:42:29Z",
      "bot": "server",
      "category": "user_update",
      "action": "user_profile_changed",
      "actor": null,
      "target": {
        "id": "1363706915024277597",
        "name": "krz_dwr",
        "discriminator": "0",
        "global_name": "ghbfv",
        "display_name": "ghbfv",
        "bot": false,
        "system": false,
        "avatar_url": "https://cdn.discordapp.com/avatars/1363706915024277597/80dab05a1ceb880c8b7b6f406658df7c.png?size=1024",
        "public_flags": 0,
        "public_flag_names": [],
        "created_at": "2025-04-21T02:44:24.991000+00:00"
      },
      "details": {
        "changes": {
          "global_name": {
            "before": "1166",
            "after": "ghbfv"
          }
        }
      },
      "guild_id": null,
      "guild_name": null
    },
    {
      "timestamp": "2026-05-29T05:42:46Z",
      "bot": "server",
      "category": "user_update",
      "action": "user_profile_changed",
      "actor": null,
      "target": {
        "id": "638535019488346123",
        "name": "behny7696",
        "discriminator": "0",
        "global_name": "Behny",
        "display_name": "Behny",
        "bot": false,
        "system": false,
        "avatar_url": "https://cdn.discordapp.com/avatars/638535019488346123/09d8a49bea92d35ae8d75ae5dad331b5.png?size=1024",
        "public_flags": 0,
        "public_flag_names": [],
        "created_at": "2019-10-29T00:30:12.053000+00:00"
      },
      "details": {
        "changes": {
          "avatar_url": {
            "before": "https://cdn.discordapp.com/avatars/638535019488346123/d003a4cae546c7cb029d70c5d621fbd7.png?size=1024",
            "after": "https://cdn.discordapp.com/avatars/638535019488346123/09d8a49bea92d35ae8d75ae5dad331b5.png?size=1024"
          }
        }
      },
      "guild_id": null,
      "guild_name": null
    },
    {
      "timestamp": "2026-05-29T05:43:15Z",
      "bot": "server",
      "category": "user_update",
      "action": "user_profile_changed",
      "actor": null,
      "target": {
        "id": "1258813781450948709",
        "name": "clxudzfnx",
        "discriminator": "0",
        "display_name": "clxudzfnx",
        "bot": false,
        "system": false,
        "avatar_url": "https://cdn.discordapp.com/avatars/1258813781450948709/841a485e284c281008c3c27fddb5228c.png?size=1024",
        "public_flags": 0,
        "public_flag_names": [],
        "created_at": "2024-07-05T15:56:33.127000+00:00"
      },
      "details": {
        "changes": {
          "avatar_url": {
            "before": "https://cdn.discordapp.com/avatars/1258813781450948709/f28ac29b38c5cb5a301a4609a2989d84.png?size=1024",
            "after": "https://cdn.discordapp.com/avatars/1258813781450948709/841a485e284c281008c3c27fddb5228c.png?size=1024"
          }
        }
      },
      "guild_id": null,
      "guild_name": null
    },
    {
      "timestamp": "2026-05-29T05:43:51Z",
      "bot": "server",
      "category": "user_update",
      "action": "user_profile_changed",
      "actor": null,
      "target": {
        "id": "1448093845140144311",
        "name": "3loyy",
        "discriminator": "0",
        "global_name": "CorTador",
        "display_name": "CorTador",
        "bot": false,
        "system": false,
        "avatar_url": "https://cdn.discordapp.com/avatars/1448093845140144311/4780354611b2b0ed8e70b172dfa6ff50.png?size=1024",
        "public_flags": 0,
        "public_flag_names": [],
        "created_at": "2025-12-09T23:27:56.964000+00:00"
      },
      "details": {
        "changes": {
          "avatar_url": {
            "before": "https://cdn.discordapp.com/avatars/1448093845140144311/364ae90fbfed4e16b12eed3654c0bc80.png?size=1024",
            "after": "https://cdn.discordapp.com/avatars/1448093845140144311/4780354611b2b0ed8e70b172dfa6ff50.png?size=1024"
          }
        }
      },
      "guild_id": null,
      "guild_name": null
    },
    {
      "timestamp": "2026-05-29T05:43:54Z",
      "bot": "server",
      "category": "user_update",
      "action": "user_profile_changed",
      "actor": null,
      "target": {
        "id": "1127524409092083762",
        "name": "chistodontforget",
        "discriminator": "0",
        "global_name": "* \u00b3\u2077\u2078 \u00b2\u2070 \u00b9\u2075 *",
        "display_name": "* \u00b3\u2077\u2078 \u00b2\u2070 \u00b9\u2075 *",
        "bot": false,
        "system": false,
        "avatar_url": "https://cdn.discordapp.com/avatars/1127524409092083762/ae04139933a17e38ca1d0eaa9ff4a914.png?size=1024",
        "public_flags": 0,
        "public_flag_names": [],
        "created_at": "2023-07-09T08:59:27.518000+00:00"
      },
      "details": {
        "changes": {
          "avatar_url": {
            "before": "https://cdn.discordapp.com/avatars/1127524409092083762/35cbb1f0821466779650915584618fd3.png?size=1024",
            "after": "https://cdn.discordapp.com/avatars/1127524409092083762/ae04139933a17e38ca1d0eaa9ff4a914.png?size=1024"
          }
        }
      },
      "guild_id": null,
      "guild_name": null
    },
    {
      "timestamp": "2026-05-29T05:44:17Z",
      "bot": "server",
      "category": "user_update",
      "action": "user_profile_changed",
      "actor": null,
      "target": {
        "id": "956786386449608735",
        "name": "rtazii",
        "discriminator": "0",
        "global_name": "rtazii!",
        "display_name": "rtazii!",
        "bot": false,
        "system": false,
        "avatar_url": "https://cdn.discordapp.com/avatars/956786386449608735/3904b852de0ae4e7d1bdb6836ebcb1e5.png?size=1024",
        "public_flags": 0,
        "public_flag_names": [],
        "created_at": "2022-03-25T05:27:30.761000+00:00"
      },
      "details": {
        "changes": {
          "avatar_url": {
            "before": "https://cdn.discordapp.com/avatars/956786386449608735/a_3904b852de0ae4e7d1bdb6836ebcb1e5.gif?size=1024",
            "after": "https://cdn.discordapp.com/avatars/956786386449608735/3904b852de0ae4e7d1bdb6836ebcb1e5.png?size=1024"
          }
        }
      },
      "guild_id": null,
      "guild_name": null
    }
  ]
}