{
  "pushed_at": "2026-06-01T19:20:39Z",
  "events": [
    {
      "timestamp": "2026-06-01T19:16:55Z",
      "bot": "server",
      "category": "member_role_update",
      "action": "member_roles_changed",
      "actor": null,
      "target": {
        "id": "1412460194918699068",
        "name": "quirrel0159",
        "discriminator": "0",
        "global_name": "Quirrel",
        "display_name": "Quirrel",
        "bot": false,
        "system": false,
        "pending": false,
        "avatar_url": "https://cdn.discordapp.com/embed/avatars/4.png",
        "public_flags": 0,
        "public_flag_names": [],
        "created_at": "2025-09-02T15:32:32.710000+00:00",
        "joined_at": "2026-06-01T19:16:53.884984+00:00",
        "roles": [
          {
            "id": "1210764975090438155",
            "name": "Member",
            "position": 22,
            "color": "#ff0000"
          }
        ],
        "top_role": "Member",
        "guild_permissions": 5224864484865
      },
      "details": {
        "added": [
          {
            "id": "1210764975090438155",
            "name": "Member",
            "position": 22,
            "color": "#ff0000",
            "hoist": false,
            "mentionable": false,
            "managed": false,
            "permissions": 5224864484865,
            "permission_names": [
              "create_instant_invite",
              "stream",
              "read_messages",
              "send_messages",
              "read_message_history",
              "connect",
              "speak",
              "use_voice_activation",
              "use_application_commands",
              "send_messages_in_threads",
              "use_embedded_activities",
              "use_soundboard"
            ]
          }
        ],
        "removed": [],
        "audit": {
          "audit_id": "1511086156685508659",
          "actor": {
            "id": "204255221017214977",
            "name": "YAGPDB.xyz",
            "discriminator": "8760",
            "display_name": "YAGPDB.xyz",
            "bot": true,
            "system": false,
            "pending": false,
            "avatar_url": "https://cdn.discordapp.com/avatars/204255221017214977/a_f745fbd1c07799ac4ec443e988e2b766.gif?size=1024",
            "public_flags": 65536,
            "public_flag_names": [
              "verified_bot"
            ],
            "created_at": "2016-07-17T15:17:19.569000+00:00",
            "joined_at": "2024-02-26T09:46:21.505000+00:00",
            "roles": [
              {
                "id": "1490579498884665425",
                "name": "*",
                "position": 1,
                "color": "#000000"
              },
              {
                "id": "1306357759163498496",
                "name": "English \ud83c\uddec\ud83c\udde7",
                "position": 9,
                "color": "#000000"
              },
              {
                "id": "1210764975090438155",
                "name": "Member",
                "position": 22,
                "color": "#ff0000"
              },
              {
                "id": "1305277560086593546",
                "name": "Manual Named Locations",
                "position": 23,
                "color": "#ff8000"
              },
              {
                "id": "1210801655663300618",
                "name": "Bots",
                "position": 72,
                "color": "#000000"
              },
              {
                "id": "1211610196208787480",
                "name": "YAGPDB.xyz",
                "position": 81,
                "color": "#000000"
              }
            ],
            "top_role": "YAGPDB.xyz",
            "guild_permissions": 1829587348619263
          },
          "reason": null,
          "created_at": "2026-06-01T19:16:54.377000+00:00",
          "changes": [
            {
              "key": "roles",
              "before": "[]",
              "after": "[<Role id=1210764975090438155 name='Member'>]"
            }
          ]
        }
      },
      "guild_id": "988564962802810961",
      "guild_name": "Wave Free Dropmaps!"
    },
    {
      "timestamp": "2026-06-01T19:17:13Z",
      "bot": "server",
      "category": "member_role_update",
      "action": "member_roles_changed",
      "actor": null,
      "target": {
        "id": "1412460194918699068",
        "name": "quirrel0159",
        "discriminator": "0",
        "global_name": "Quirrel",
        "display_name": "Quirrel",
        "bot": false,
        "system": false,
        "pending": false,
        "avatar_url": "https://cdn.discordapp.com/embed/avatars/4.png",
        "public_flags": 0,
        "public_flag_names": [],
        "created_at": "2025-09-02T15:32:32.710000+00:00",
        "joined_at": "2026-06-01T19:16:53.884984+00:00",
        "roles": [
          {
            "id": "1306357759163498496",
            "name": "English \ud83c\uddec\ud83c\udde7",
            "position": 9,
            "color": "#000000"
          },
          {
            "id": "1210764376676634684",
            "name": "Invite Way",
            "position": 20,
            "color": "#000000"
          },
          {
            "id": "1210764975090438155",
            "name": "Member",
            "position": 22,
            "color": "#ff0000"
          }
        ],
        "top_role": "Member",
        "guild_permissions": 5224864484865
      },
      "details": {
        "added": [
          {
            "id": "1306357759163498496",
            "name": "English \ud83c\uddec\ud83c\udde7",
            "position": 9,
            "color": "#000000",
            "hoist": false,
            "mentionable": false,
            "managed": false,
            "permissions": 0,
            "permission_names": []
          },
          {
            "id": "1210764376676634684",
            "name": "Invite Way",
            "position": 20,
            "color": "#000000",
            "hoist": false,
            "mentionable": false,
            "managed": false,
            "permissions": 0,
            "permission_names": []
          }
        ],
        "removed": [],
        "audit": {
          "audit_id": "1511086232757866536",
          "actor": {
            "id": "1412460194918699068",
            "name": "quirrel0159",
            "discriminator": "0",
            "global_name": "Quirrel",
            "display_name": "Quirrel",
            "bot": false,
            "system": false,
            "pending": false,
            "avatar_url": "https://cdn.discordapp.com/embed/avatars/4.png",
            "public_flags": 0,
            "public_flag_names": [],
            "created_at": "2025-09-02T15:32:32.710000+00:00",
            "joined_at": "2026-06-01T19:16:53.884984+00:00",
            "roles": [
              {
                "id": "1306357759163498496",
                "name": "English \ud83c\uddec\ud83c\udde7",
                "position": 9,
                "color": "#000000"
              },
              {
                "id": "1210764376676634684",
                "name": "Invite Way",
                "position": 20,
                "color": "#000000"
              },
              {
                "id": "1210764975090438155",
                "name": "Member",
                "position": 22,
                "color": "#ff0000"
              }
            ],
            "top_role": "Member",
            "guild_permissions": 5224864484865
          },
          "reason": null,
          "created_at": "2026-06-01T19:17:12.514000+00:00",
          "changes": [
            {
              "key": "roles",
              "before": "[]",
              "after": "[<Role id=1306357759163498496 name='English \ud83c\uddec\ud83c\udde7'>, <Role id=1210764376676634684 name='Invite Way'>]"
            }
          ]
        }
      },
      "guild_id": "988564962802810961",
      "guild_name": "Wave Free Dropmaps!"
    },
    {
      "timestamp": "2026-06-01T19:17:22Z",
      "bot": "server",
      "category": "member_role_update",
      "action": "member_roles_changed",
      "actor": null,
      "target": {
        "id": "696088640945651734",
        "name": "gabriel2346",
        "discriminator": "0",
        "global_name": "Gabe the Babe",
        "display_name": "Gabe the Babe",
        "bot": false,
        "system": false,
        "pending": false,
        "avatar_url": "https://cdn.discordapp.com/avatars/696088640945651734/1fd8fbb88f06538e4318729dd08df047.png?size=1024",
        "public_flags": 0,
        "public_flag_names": [],
        "created_at": "2020-04-04T20:07:44.703000+00:00",
        "joined_at": "2026-05-12T15:44:40.974000+00:00",
        "roles": [
          {
            "id": "1483009677137547415",
            "name": "Deutsch \ud83c\udde9\ud83c\uddea",
            "position": 8,
            "color": "#000000"
          },
          {
            "id": "1210764376676634684",
            "name": "Invite Way",
            "position": 20,
            "color": "#000000"
          },
          {
            "id": "1210764975090438155",
            "name": "Member",
            "position": 22,
            "color": "#ff0000"
          },
          {
            "id": "1305277560086593546",
            "name": "Manual Named Locations",
            "position": 23,
            "color": "#ff8000"
          },
          {
            "id": "1055713830988157039",
            "name": "Manual Landmarks",
            "position": 24,
            "color": "#ffff00"
          }
        ],
        "top_role": "Manual Landmarks",
        "guild_permissions": 5224864484865
      },
      "details": {
        "added": [],
        "removed": [
          {
            "id": "1467355713692106752",
            "name": "Server Tag User",
            "position": 19,
            "color": "#000000",
            "hoist": false,
            "mentionable": false,
            "managed": false,
            "permissions": 0,
            "permission_names": []
          }
        ],
        "audit": {
          "audit_id": "1511086269403496499",
          "actor": {
            "id": "697487580522086431",
            "name": "AutoMod",
            "discriminator": "8695",
            "display_name": "Use Code Fruss For Access!",
            "nick": "Use Code Fruss For Access!",
            "bot": true,
            "system": false,
            "pending": false,
            "avatar_url": "https://cdn.discordapp.com/avatars/697487580522086431/932397508df8560ddf1514619184947c.png?size=1024",
            "public_flags": 65536,
            "public_flag_names": [
              "verified_bot"
            ],
            "created_at": "2020-04-08T16:46:37.889000+00:00",
            "joined_at": "2024-05-27T11:46:40.308000+00:00",
            "roles": [
              {
                "id": "1490579498884665425",
                "name": "*",
                "position": 1,
                "color": "#000000"
              },
              {
                "id": "1306357759163498496",
                "name": "English \ud83c\uddec\ud83c\udde7",
                "position": 9,
                "color": "#000000"
              },
              {
                "id": "1210764975090438155",
                "name": "Member",
                "position": 22,
                "color": "#ff0000"
              },
              {
                "id": "1305277560086593546",
                "name": "Manual Named Locations",
                "position": 23,
                "color": "#ff8000"
              },
              {
                "id": "1210801655663300618",
                "name": "Bots",
                "position": 72,
                "color": "#000000"
              },
              {
                "id": "1244617769937403907",
                "name": "AutoMod",
                "position": 73,
                "color": "#000000"
              }
            ],
            "top_role": "AutoMod",
            "guild_permissions": 1829587348619263
          },
          "reason": null,
          "created_at": "2026-06-01T19:17:21.251000+00:00",
          "changes": [
            {
              "key": "roles",
              "before": "[<Role id=1467355713692106752 name='Server Tag User'>]",
              "after": "[]"
            }
          ]
        }
      },
      "guild_id": "988564962802810961",
      "guild_name": "Wave Free Dropmaps!"
    }
  ]
}