{
  "pushed_at": "2026-05-28T11:29:51Z",
  "events": [
    {
      "timestamp": "2026-05-28T11:25:33Z",
      "bot": "server",
      "category": "user_update",
      "action": "user_profile_changed",
      "actor": null,
      "target": {
        "id": "1210351967071764511",
        "name": "ef4no.tv",
        "discriminator": "0",
        "global_name": "qvr\u2730!",
        "display_name": "qvr\u2730!",
        "bot": false,
        "system": false,
        "avatar_url": "https://cdn.discordapp.com/avatars/1210351967071764511/3e93860ff053d7e535227a6def036556.png?size=1024",
        "public_flags": 64,
        "public_flag_names": [
          "hypesquad_bravery"
        ],
        "created_at": "2024-02-22T22:26:36.202000+00:00"
      },
      "details": {
        "changes": {
          "avatar_url": {
            "before": "https://cdn.discordapp.com/avatars/1210351967071764511/e494a7654ec8a8361f7432c59cc8eea8.png?size=1024",
            "after": "https://cdn.discordapp.com/avatars/1210351967071764511/3e93860ff053d7e535227a6def036556.png?size=1024"
          }
        }
      },
      "guild_id": null,
      "guild_name": null
    },
    {
      "timestamp": "2026-05-28T11:25:41Z",
      "bot": "server",
      "category": "user_update",
      "action": "user_profile_changed",
      "actor": null,
      "target": {
        "id": "842430150775144490",
        "name": "zelfiie",
        "discriminator": "0",
        "display_name": "zelfiie",
        "bot": false,
        "system": false,
        "avatar_url": "https://cdn.discordapp.com/avatars/842430150775144490/10f355492fdd180e2308137c6ca9e67d.png?size=1024",
        "public_flags": 128,
        "public_flag_names": [
          "hypesquad_brilliance"
        ],
        "created_at": "2021-05-13T15:56:39.540000+00:00"
      },
      "details": {
        "changes": {
          "global_name": {
            "before": "theriosa",
            "after": null
          }
        }
      },
      "guild_id": null,
      "guild_name": null
    },
    {
      "timestamp": "2026-05-28T11:25:54Z",
      "bot": "server",
      "category": "user_update",
      "action": "user_profile_changed",
      "actor": null,
      "target": {
        "id": "1059476764490993734",
        "name": "versnxzx313",
        "discriminator": "0",
        "global_name": "versnfv",
        "display_name": "versnfv",
        "bot": false,
        "system": false,
        "avatar_url": "https://cdn.discordapp.com/avatars/1059476764490993734/4b1707959f116d9bbf7f195557a78a58.png?size=1024",
        "public_flags": 0,
        "public_flag_names": [],
        "created_at": "2023-01-02T14:22:24.781000+00:00"
      },
      "details": {
        "changes": {
          "avatar_url": {
            "before": "https://cdn.discordapp.com/avatars/1059476764490993734/4bed58fca4ce1f4510de3c5eb0d39eb6.png?size=1024",
            "after": "https://cdn.discordapp.com/avatars/1059476764490993734/4b1707959f116d9bbf7f195557a78a58.png?size=1024"
          }
        }
      },
      "guild_id": null,
      "guild_name": null
    },
    {
      "timestamp": "2026-05-28T11:26:48Z",
      "bot": "server",
      "category": "user_update",
      "action": "user_profile_changed",
      "actor": null,
      "target": {
        "id": "989646990843449374",
        "name": "flm_amar",
        "discriminator": "0",
        "global_name": "AmarTrades",
        "display_name": "AmarTrades",
        "bot": false,
        "system": false,
        "avatar_url": "https://cdn.discordapp.com/avatars/989646990843449374/b0a02f1b427da5c5385b3db3feb911c5.png?size=1024",
        "public_flags": 0,
        "public_flag_names": [],
        "created_at": "2022-06-23T21:43:49.369000+00:00"
      },
      "details": {
        "changes": {
          "avatar_url": {
            "before": "https://cdn.discordapp.com/avatars/989646990843449374/b7c402923d42766b007800e249026729.png?size=1024",
            "after": "https://cdn.discordapp.com/avatars/989646990843449374/b0a02f1b427da5c5385b3db3feb911c5.png?size=1024"
          }
        }
      },
      "guild_id": null,
      "guild_name": null
    },
    {
      "timestamp": "2026-05-28T11:27:24Z",
      "bot": "server",
      "category": "user_update",
      "action": "user_profile_changed",
      "actor": null,
      "target": {
        "id": "806977219263856660",
        "name": "kzvfx",
        "discriminator": "0",
        "global_name": "Kz",
        "display_name": "Kz",
        "bot": false,
        "system": false,
        "avatar_url": "https://cdn.discordapp.com/avatars/806977219263856660/1b339946cab8cdb83944c62fe6002c77.png?size=1024",
        "public_flags": 0,
        "public_flag_names": [],
        "created_at": "2021-02-04T19:59:21.984000+00:00"
      },
      "details": {
        "changes": {
          "avatar_url": {
            "before": "https://cdn.discordapp.com/avatars/806977219263856660/3236504b2efc6e84ce789e895bd5fe42.png?size=1024",
            "after": "https://cdn.discordapp.com/avatars/806977219263856660/1b339946cab8cdb83944c62fe6002c77.png?size=1024"
          }
        }
      },
      "guild_id": null,
      "guild_name": null
    },
    {
      "timestamp": "2026-05-28T11:27:38Z",
      "bot": "server",
      "category": "user_update",
      "action": "user_profile_changed",
      "actor": null,
      "target": {
        "id": "1392948541772660766",
        "name": "eluplayfn",
        "discriminator": "0",
        "global_name": "elu 7 yhyh.",
        "display_name": "elu 7 yhyh.",
        "bot": false,
        "system": false,
        "avatar_url": "https://cdn.discordapp.com/avatars/1392948541772660766/d7faf4ecd01f8f2ecf488f3744434bd5.png?size=1024",
        "public_flags": 0,
        "public_flag_names": [],
        "created_at": "2025-07-10T19:20:12.091000+00:00"
      },
      "details": {
        "changes": {
          "avatar_url": {
            "before": "https://cdn.discordapp.com/avatars/1392948541772660766/694fc8c40cb0736d28e26fb77e6b96bd.png?size=1024",
            "after": "https://cdn.discordapp.com/avatars/1392948541772660766/d7faf4ecd01f8f2ecf488f3744434bd5.png?size=1024"
          }
        }
      },
      "guild_id": null,
      "guild_name": null
    },
    {
      "timestamp": "2026-05-28T11:27:38Z",
      "bot": "server",
      "category": "user_update",
      "action": "user_profile_changed",
      "actor": null,
      "target": {
        "id": "1031650302941724772",
        "name": "veinsofsorrow",
        "discriminator": "0",
        "display_name": "veinsofsorrow",
        "bot": false,
        "system": false,
        "avatar_url": "https://cdn.discordapp.com/avatars/1031650302941724772/e858aa1b45acaa7bc2f677917bf2cb66.png?size=1024",
        "public_flags": 0,
        "public_flag_names": [],
        "created_at": "2022-10-17T19:29:59.357000+00:00"
      },
      "details": {
        "changes": {
          "name": {
            "before": "rotttttt",
            "after": "veinsofsorrow"
          }
        }
      },
      "guild_id": null,
      "guild_name": null
    },
    {
      "timestamp": "2026-05-28T11:28:06Z",
      "bot": "server",
      "category": "user_update",
      "action": "user_profile_changed",
      "actor": null,
      "target": {
        "id": "1266779757240914040",
        "name": "mandelal",
        "discriminator": "0",
        "global_name": "abu",
        "display_name": "abu",
        "bot": false,
        "system": false,
        "avatar_url": "https://cdn.discordapp.com/avatars/1266779757240914040/a730bbab9d2520435a2a2aa268e48eb5.png?size=1024",
        "public_flags": 0,
        "public_flag_names": [],
        "created_at": "2024-07-27T15:30:29.756000+00:00"
      },
      "details": {
        "changes": {
          "avatar_url": {
            "before": "https://cdn.discordapp.com/avatars/1266779757240914040/781cc4262c406af4e96712f11ffed265.png?size=1024",
            "after": "https://cdn.discordapp.com/avatars/1266779757240914040/a730bbab9d2520435a2a2aa268e48eb5.png?size=1024"
          }
        }
      },
      "guild_id": null,
      "guild_name": null
    },
    {
      "timestamp": "2026-05-28T11:28:51Z",
      "bot": "server",
      "category": "user_update",
      "action": "user_profile_changed",
      "actor": null,
      "target": {
        "id": "856988234637901834",
        "name": "saintfkn",
        "discriminator": "0",
        "global_name": "saint",
        "display_name": "saint",
        "bot": false,
        "system": false,
        "avatar_url": "https://cdn.discordapp.com/avatars/856988234637901834/ddda0086152dd9ca626c655868fbf47b.png?size=1024",
        "public_flags": 128,
        "public_flag_names": [
          "hypesquad_brilliance"
        ],
        "created_at": "2021-06-22T20:05:17.209000+00:00"
      },
      "details": {
        "changes": {
          "avatar_url": {
            "before": "https://cdn.discordapp.com/avatars/856988234637901834/4e927af204071c7caa87a541a21582e0.png?size=1024",
            "after": "https://cdn.discordapp.com/avatars/856988234637901834/ddda0086152dd9ca626c655868fbf47b.png?size=1024"
          }
        }
      },
      "guild_id": null,
      "guild_name": null
    },
    {
      "timestamp": "2026-05-28T11:29:24Z",
      "bot": "server",
      "category": "user_update",
      "action": "user_profile_changed",
      "actor": null,
      "target": {
        "id": "1445252666275008547",
        "name": "zzzxay.1",
        "discriminator": "0",
        "global_name": "XayGOTY 7",
        "display_name": "XayGOTY 7",
        "bot": false,
        "system": false,
        "avatar_url": "https://cdn.discordapp.com/avatars/1445252666275008547/a2751436c4562f25a684096b6a6282f0.png?size=1024",
        "public_flags": 0,
        "public_flag_names": [],
        "created_at": "2025-12-02T03:18:07.136000+00:00"
      },
      "details": {
        "changes": {
          "avatar_url": {
            "before": "https://cdn.discordapp.com/avatars/1445252666275008547/f1619ed888df4bc2f5f68b69febe8d4a.png?size=1024",
            "after": "https://cdn.discordapp.com/avatars/1445252666275008547/a2751436c4562f25a684096b6a6282f0.png?size=1024"
          }
        }
      },
      "guild_id": null,
      "guild_name": null
    }
  ]
}