{
  "pushed_at": "2026-05-25T22:57:57Z",
  "events": [
    {
      "timestamp": "2026-05-25T22:45:41Z",
      "bot": "server",
      "category": "role_changes",
      "action": "member_roles_changed",
      "actor": null,
      "target": {
        "id": "1263775996931346484",
        "name": "gxr_sprxk.",
        "display_name": "\ud835\udc00\ud835\udc31\ud835\udc2c\ud835\udc2d\ud835\udc2b\ud835\udc28\uaa04\u2655\u2740",
        "global_name": "\ud835\udc00\ud835\udc31\ud835\udc2c\ud835\udc2d\ud835\udc2b\ud835\udc28\uaa04\u2655\u2740",
        "avatar_url": "https://cdn.discordapp.com/avatars/1263775996931346484/2b48da37e4bfc12f1c76aa4ba7dc81b4.png?size=1024",
        "top_role": "Manual Named Locations"
      },
      "details": {
        "added": [
          {
            "id": "1305277560086593546",
            "name": "Manual Named Locations"
          }
        ],
        "removed": []
      },
      "guild_id": "988564962802810961",
      "guild_name": "Wave Free Dropmaps!"
    },
    {
      "timestamp": "2026-05-25T22:45:45Z",
      "bot": "server",
      "category": "role_changes",
      "action": "member_roles_changed",
      "actor": null,
      "target": {
        "id": "1263775996931346484",
        "name": "gxr_sprxk.",
        "display_name": "\ud835\udc00\ud835\udc31\ud835\udc2c\ud835\udc2d\ud835\udc2b\ud835\udc28\uaa04\u2655\u2740",
        "global_name": "\ud835\udc00\ud835\udc31\ud835\udc2c\ud835\udc2d\ud835\udc2b\ud835\udc28\uaa04\u2655\u2740",
        "avatar_url": "https://cdn.discordapp.com/avatars/1263775996931346484/2b48da37e4bfc12f1c76aa4ba7dc81b4.png?size=1024",
        "top_role": "Manual Landmarks"
      },
      "details": {
        "added": [
          {
            "id": "1055713830988157039",
            "name": "Manual Landmarks"
          }
        ],
        "removed": []
      },
      "guild_id": "988564962802810961",
      "guild_name": "Wave Free Dropmaps!"
    },
    {
      "timestamp": "2026-05-25T22:46:47Z",
      "bot": "server",
      "category": "role_changes",
      "action": "member_roles_changed",
      "actor": null,
      "target": {
        "id": "1419022360014622752",
        "name": "sahil190711",
        "display_name": "sahil",
        "global_name": "sahil",
        "avatar_url": "https://cdn.discordapp.com/avatars/1419022360014622752/555d3896796cf22211bbeaa04b59287d.png?size=1024",
        "top_role": "Manual Named Locations"
      },
      "details": {
        "added": [
          {
            "id": "1305277560086593546",
            "name": "Manual Named Locations"
          }
        ],
        "removed": []
      },
      "guild_id": "988564962802810961",
      "guild_name": "Wave Free Dropmaps!"
    },
    {
      "timestamp": "2026-05-25T22:48:01Z",
      "bot": "server",
      "category": "role_changes",
      "action": "member_roles_changed",
      "actor": null,
      "target": {
        "id": "1419022360014622752",
        "name": "sahil190711",
        "display_name": "sahil",
        "global_name": "sahil",
        "avatar_url": "https://cdn.discordapp.com/avatars/1419022360014622752/555d3896796cf22211bbeaa04b59287d.png?size=1024",
        "top_role": "Member"
      },
      "details": {
        "added": [
          {
            "id": "1149680236041080832",
            "name": "Member"
          }
        ],
        "removed": []
      },
      "guild_id": "971731167621574666",
      "guild_name": "Wave Improvement Cord! | Loot Routes + Tips & Tricks"
    },
    {
      "timestamp": "2026-05-25T22:48:11Z",
      "bot": "server",
      "category": "role_changes",
      "action": "member_roles_changed",
      "actor": null,
      "target": {
        "id": "1419022360014622752",
        "name": "sahil190711",
        "display_name": "sahil",
        "global_name": "sahil",
        "avatar_url": "https://cdn.discordapp.com/avatars/1419022360014622752/555d3896796cf22211bbeaa04b59287d.png?size=1024",
        "top_role": "Member"
      },
      "details": {
        "added": [
          {
            "id": "1188092082540261486",
            "name": "Code Way"
          }
        ],
        "removed": []
      },
      "guild_id": "971731167621574666",
      "guild_name": "Wave Improvement Cord! | Loot Routes + Tips & Tricks"
    },
    {
      "timestamp": "2026-05-25T22:52:49Z",
      "bot": "server",
      "category": "role_changes",
      "action": "member_roles_changed",
      "actor": null,
      "target": {
        "id": "1419022360014622752",
        "name": "sahil190711",
        "display_name": "sahil",
        "global_name": "sahil",
        "avatar_url": "https://cdn.discordapp.com/avatars/1419022360014622752/555d3896796cf22211bbeaa04b59287d.png?size=1024",
        "top_role": "Manual Landmarks"
      },
      "details": {
        "added": [
          {
            "id": "1055713830988157039",
            "name": "Manual Landmarks"
          }
        ],
        "removed": []
      },
      "guild_id": "988564962802810961",
      "guild_name": "Wave Free Dropmaps!"
    },
    {
      "timestamp": "2026-05-25T22:56:17Z",
      "bot": "server",
      "category": "role_changes",
      "action": "member_roles_changed",
      "actor": null,
      "target": {
        "id": "1419022360014622752",
        "name": "sahil190711",
        "display_name": "sahil",
        "global_name": "sahil",
        "avatar_url": "https://cdn.discordapp.com/avatars/1419022360014622752/555d3896796cf22211bbeaa04b59287d.png?size=1024",
        "top_role": "Access"
      },
      "details": {
        "added": [
          {
            "id": "1105873031450075227",
            "name": "Access"
          }
        ],
        "removed": []
      },
      "guild_id": "971731167621574666",
      "guild_name": "Wave Improvement Cord! | Loot Routes + Tips & Tricks"
    },
    {
      "timestamp": "2026-05-25T22:57:49Z",
      "bot": "server",
      "category": "role_changes",
      "action": "member_roles_changed",
      "actor": null,
      "target": {
        "id": "1464376289015365643",
        "name": "kxnzoee",
        "display_name": "0king",
        "global_name": "0king",
        "avatar_url": "https://cdn.discordapp.com/avatars/1464376289015365643/154502d67649851664de529decfcecf7.png?size=1024",
        "top_role": "Manual Landmarks"
      },
      "details": {
        "added": [
          {
            "id": "1467355713692106752",
            "name": "Server Tag User"
          }
        ],
        "removed": []
      },
      "guild_id": "988564962802810961",
      "guild_name": "Wave Free Dropmaps!"
    }
  ]
}